toripchanger/__init__.py
toripchanger/changer.py
toripchanger/exceptions.py
toripchanger/server.py
toripchanger-1.3.0.data/scripts/toripchanger_server
toripchanger-1.3.0.dist-info/LICENSE
toripchanger-1.3.0.dist-info/METADATA
toripchanger-1.3.0.dist-info/WHEEL
toripchanger-1.3.0.dist-info/top_level.txt
toripchanger-1.3.0.dist-info/RECORD
