Metadata-Version: 2.1
Name: toripchanger
Version: 1.3.0
Summary: Python powered way to get a unique Tor IP
Home-page: https://github.com/DusanMadar/TorIpChanger
Author: Dusan Madar
License: MIT
Keywords: change tor ip
Platform: linux
Classifier: Development Status :: 5 - Production/Stable
Classifier: Intended Audience :: Developers
Classifier: Programming Language :: Python :: 3
Classifier: Operating System :: POSIX :: Linux
Classifier: Natural Language :: English
Requires-Python: >=3.5
License-File: LICENSE
Requires-Dist: requests ==2.32.*
Requires-Dist: stem ==1.8.2
Provides-Extra: server
Requires-Dist: flask ==3.0.* ; extra == 'server'
